weavel/__init__.py
weavel/_api_client.py
weavel/_body.py
weavel/_buffer_storage.py
weavel/_constants.py
weavel/_request.py
weavel/_worker.py
weavel/client.py
weavel/object_clients.py
weavel/wrapper.py
weavel/clients/websocket_client.py
weavel/types/__init__.py
weavel/types/datasets.py
weavel/types/observations.py
weavel/types/prompts.py
weavel/types/records.py
weavel/types/session.py
weavel/types/websocket.py
weavel/utils/__init__.py
weavel/utils/logging.py
weavel/utils/security.py
weavel-1.11.0.dist-info/LICENSE
weavel-1.11.0.dist-info/METADATA
weavel-1.11.0.dist-info/WHEEL
weavel-1.11.0.dist-info/top_level.txt
weavel-1.11.0.dist-info/RECORD
