Metadata-Version: 2.1
Name: weavel
Version: 1.11.0
Summary: Weavel, automated prompt engineering and observability for LLM applications
Home-page: https://github.com/weavel-ai/weavel-python
Author: weavel
Keywords: weavel,agent,llm,evaluation,llm evaluation,prompt evaluation,dataset curation,prompt engineering,prompt optimization,AI Prompt Engineer
Requires-Python: >=3.8.10
License-File: LICENSE
Requires-Dist: httpx[http2]
Requires-Dist: pydantic >=2.4.2
Requires-Dist: typer[all]
Requires-Dist: pendulum
Requires-Dist: requests
Requires-Dist: cryptography
Requires-Dist: pyyaml
Requires-Dist: InquirerPy
Requires-Dist: python-dotenv
Requires-Dist: websockets
Requires-Dist: termcolor
Requires-Dist: watchdog
Requires-Dist: readerwriterlock
Requires-Dist: nest-asyncio
Requires-Dist: tenacity
Requires-Dist: ape-common >=0.2.0
